jsoneer.py
objectjson.py
objectjson-0.0.2.dist-info/METADATA
objectjson-0.0.2.dist-info/WHEEL
objectjson-0.0.2.dist-info/entry_points.txt
objectjson-0.0.2.dist-info/top_level.txt
objectjson-0.0.2.dist-info/RECORD
