Metadata-Version: 2.1
Name: objectjson
Version: 0.0.2
Summary: json对象操作操作工具。
Home-page: https://github.com/kancyframework/python-plugins/tree/main/objectjson
Author: kancy
Author-email: 793272861@qq.com
License: MIT
Platform: UNKNOWN
Classifier: License :: OSI Approved :: MIT License
Classifier: Programming Language :: Python
Classifier: Programming Language :: Python :: 3
Classifier: Programming Language :: Python :: 3.6
Classifier: Programming Language :: Python :: Implementation :: CPython
Classifier: Programming Language :: Python :: Implementation :: PyPy
Requires-Python: >=3
